LICENSE
simpleselenium/__init__.py
simpleselenium/browser.py
simpleselenium/data/jquery.js
simpleselenium/element_selectors.py
simpleselenium/exceptions.py
simpleselenium/js_scripts/jquery_scripts.py
simpleselenium/js_scripts/scripts.py
simpleselenium/log_config/log_config.yaml
simpleselenium/read_envs.py
simpleselenium/session.py
simpleselenium/settings.py
simpleselenium/tabs.py
simpleselenium/tests/test_basic_function.py
simpleselenium/tests/test_yahoo.py
simpleselenium/utils/__init__.py
simpleselenium/utils/core.py
simpleselenium/wait.py
simpleselenium-0.4.4.dist-info/LICENSE
simpleselenium-0.4.4.dist-info/METADATA
simpleselenium-0.4.4.dist-info/WHEEL
simpleselenium-0.4.4.dist-info/RECORD
