Metadata-Version: 2.1
Name: simpleselenium
Version: 0.4.4
Summary: Python package to easily work with Selenium.
Home-page: https://github.com/TheConfused/simpleselenium
License: MIT
Keywords: selenium,selenium python,selenium python automation,python automation
Author: Vishal Kumar Mishra
Author-email: vishal.k.mishra2@gmail.com
Requires-Python: >=3.10,<4.0
Classifier: License :: OSI Approved :: MIT License
Classifier: Programming Language :: Python :: 3
Classifier: Programming Language :: Python :: 3.10
Classifier: Programming Language :: Python :: 3.11
Requires-Dist: PyYAML (>=6.0.1,<7.0.0)
Requires-Dist: browserjquery (>=0.1.0,<0.2.0)
Requires-Dist: django-environ (>=0.11.1,<0.12.0)
Requires-Dist: pyquery (>=2.0.0,<3.0.0)
Requires-Dist: python-dotenv (>=1.0.0,<2.0.0)
Requires-Dist: selenium (>=4.12.0,<5.0.0)
Requires-Dist: webdriver-manager (==4.0.0)
Project-URL: Repository, https://github.com/TheConfused/simpleselenium
